CMakeLists.txt
socom/__init__.py
socom/_multinet.cpython-311-darwin.so
socom/net.py
socom-0.1.0.dist-info/LICENSE.txt
socom-0.1.0.dist-info/METADATA
socom-0.1.0.dist-info/WHEEL
socom-0.1.0.dist-info/RECORD
