Metadata-Version: 2.1
Name: socom
Version: 0.1.0
Summary: Data analysis tool for studying social communication
License: LICENSE
Author: Davide Vega
Author-email: davide.vega@it.uu.se
Requires-Python: >=3.10
Classifier: License :: Other/Proprietary License
Classifier: Programming Language :: Python :: 3
Classifier: Programming Language :: Python :: 3.10
Classifier: Programming Language :: Python :: 3.11
Classifier: Programming Language :: Python :: 3.12
Requires-Dist: pybind11 (>=2.8.0)
